pdf_with_js/__init__.py
pdf_with_js/plugin.py
pdf_with_js/printer.py
pdf_with_js/stylesheets/printer.css
mkdocs_pdf_with_js_plugin-0.1.3.dist-info/LICENSE
mkdocs_pdf_with_js_plugin-0.1.3.dist-info/METADATA
mkdocs_pdf_with_js_plugin-0.1.3.dist-info/WHEEL
mkdocs_pdf_with_js_plugin-0.1.3.dist-info/entry_points.txt
mkdocs_pdf_with_js_plugin-0.1.3.dist-info/top_level.txt
mkdocs_pdf_with_js_plugin-0.1.3.dist-info/RECORD
