Metadata-Version: 2.1
Name: mkdocs-pdf-with-js-plugin
Version: 0.1.3
Summary: A MkDocs plugin that exports your documentation as PDF with rendered JavaScript content.
Home-page: https://github.com/smaxtec/mkdocs-pdf-with-js-plugin
Author: Stefan Brandstaetter
Author-email: stefan.brandstaetter@smaxtec.com
License: MIT
Keywords: mkdocs pdf javascript selenium
Platform: UNKNOWN
Classifier: Development Status :: 4 - Beta
Classifier: Intended Audience :: Developers
Classifier: Intended Audience :: Information Technology
Classifier: License :: OSI Approved :: MIT License
Classifier: Topic :: Documentation
Classifier: Topic :: Printing
Classifier: Programming Language :: Python
Classifier: Programming Language :: Python :: 3 :: Only
Classifier: Programming Language :: Python :: 3.4
Classifier: Programming Language :: Python :: 3.5
Classifier: Programming Language :: Python :: 3.6
Classifier: Programming Language :: Python :: 3.7
Requires-Python: >=3.4
Requires-Dist: beautifulsoup4
Requires-Dist: mkdocs (>=1.0.4)
Requires-Dist: selenium
